logging_plugins/__init__.py
logging_plugins/cli.py
logging_plugins-0.0.2.dist-info/DESCRIPTION.rst
logging_plugins-0.0.2.dist-info/METADATA
logging_plugins-0.0.2.dist-info/RECORD
logging_plugins-0.0.2.dist-info/WHEEL
logging_plugins-0.0.2.dist-info/metadata.json
logging_plugins-0.0.2.dist-info/top_level.txt
